tb_variant_filter/__init__.py
tb_variant_filter/bed_to_regions_cli.py
tb_variant_filter/cli.py
tb_variant_filter/region_list.py
tb_variant_filter/regions_to_bed.py
tb_variant_filter/filters/__init__.py
tb_variant_filter/filters/alt_percentage_filter.py
tb_variant_filter/filters/close_to_indel_filter.py
tb_variant_filter/filters/min_depth_filter.py
tb_variant_filter/filters/region_filter.py
tb_variant_filter/filters/snv_only_filter.py
tb_variant_filter/masks/__init__.py
tb_variant_filter/masks/farhat_rlc.py
tb_variant_filter/masks/farhat_rlc_lowmap.py
tb_variant_filter/masks/mtbseq.py
tb_variant_filter/masks/pe_ppe.py
tb_variant_filter/masks/tbprofiler.py
tb_variant_filter/masks/uvp.py
tests/__init__.py
tests/test_alt_percentage_filter.py
tests/test_close_to_indel_filter.py
tests/test_farhat_rlc.py
tests/test_farhat_rlc_lowmap.py
tests/test_min_depth_filter.py
tests/test_mtbseq.py
tests/test_multiple_ann_records.py
tests/test_pe_ppe.py
tests/test_region_filter.py
tests/test_region_list.py
tests/test_snv_filter.py
tests/test_tbprofiler.py
tests/test_uvp.py
tests/utils.py
tb_variant_filter-0.4.0.dist-info/COPYING
tb_variant_filter-0.4.0.dist-info/METADATA
tb_variant_filter-0.4.0.dist-info/WHEEL
tb_variant_filter-0.4.0.dist-info/entry_points.txt
tb_variant_filter-0.4.0.dist-info/top_level.txt
tb_variant_filter-0.4.0.dist-info/RECORD
