Metadata-Version: 2.1
Name: tb-variant-filter
Version: 0.4.0
Summary: This tool offers multiple options for filtering variants (in VCF files, relative to M. tuberculosis H37Rv).
Home-page: https://github.com/COMBAT-TB/tb_variant_filter
Author: "Peter van Heusden"
Author-email: pvh@sanbi.ac.za
License: GPLv3
Keywords: bioinformatics,tuberculosis
Classifier: Development Status :: 4 - Beta
Classifier: Environment :: Console
Classifier: License :: OSI Approved :: GNU General Public License v3 or later (GPLv3+)
Classifier: Intended Audience :: Science/Research
Classifier: Topic :: Scientific/Engineering
Classifier: Topic :: Scientific/Engineering :: Bio-Informatics
Classifier: Programming Language :: Python :: 3
Classifier: Operating System :: POSIX :: Linux
Requires-Python: >=3.7
License-File: COPYING
Requires-Dist: intervaltree
Requires-Dist: lxml
Requires-Dist: pandas
Requires-Dist: vcfpy
Requires-Dist: requests
Requires-Dist: neo4j
Provides-Extra: test
Requires-Dist: pytest >=6 ; extra == 'test'
